[
    {
        "input_combination": [
            {
                "type": 1,
                "code": 58,
                "origin_hash": "355bf3178ada138ac3dcc3eb429f4397"
            }
        ],
        "target_uinput": "keyboard",
        "output_symbol": "XF86LaunchA",
        "mapping_type": "key_macro"
    },
    {
        "input_combination": [
            {
                "type": 1,
                "code": 164,
                "origin_hash": "3b068f7d5a5a164c6c43b498cea0941b"
            }
        ],
        "target_uinput": "keyboard",
        "output_symbol": "XF86AudioRecord",
        "mapping_type": "key_macro"
    }
]
